aps/__init__.py
aps/beamline_driver/__init__.py
aps/beamline_driver/facade.py
aps/beamline_driver/adapters/__init__.py
aps/beamline_driver/adapters/ophyd/__init__.py
aps/beamline_driver/adapters/ophyd/detector.py
aps/beamline_driver/adapters/ophyd/detector_factory.py
aps/beamline_driver/adapters/ophyd/motor.py
aps/beamline_driver/beam_management/__init__.py
aps/beamline_driver/beam_management/abstract_beam_manager.py
aps/beamline_driver/beam_management/beam_manager_factory.py
aps/beamline_driver/beam_management/facade.py
aps/beamline_driver/beam_management/control_systems/__init__.py
aps/beamline_driver/beam_management/control_systems/common.py
aps/beamline_driver/beam_management/control_systems/bluesky/__init__.py
aps/beamline_driver/beam_management/control_systems/epics/__init__.py
aps/beamline_driver/beam_management/control_systems/epics/epics_camera_beam_manager.py
aps/beamline_driver/beam_management/control_systems/epics/epics_scan_beam_manager.py
aps/beamline_driver/beam_management/control_systems/epics/epics_wavefront_analyzer_beam_manager.py
aps/beamline_driver/beam_management/control_systems/epics/_denoise_test/__init__.py
aps/beamline_driver/beam_management/control_systems/epics/_denoise_test/tiff_denoise.py
aps/beamline_driver/beam_management/control_systems/epics/_denoise_test/tiff_multi_otsu_denoise.py
aps/beamline_driver/beam_management/digital_twin/__init__.py
aps/beamline_driver/beam_management/digital_twin/shadow4/__init__.py
aps/beamline_driver/beam_management/digital_twin/shadow4/s4_beam_manager.py
aps/beamline_driver/beam_management/digital_twin/srw/__init__.py
aps/beamline_driver/beam_management/digital_twin/srw/srw_beam_manager.py
aps/beamline_driver/common/__init__.py
aps/beamline_driver/common/bluesky.py
aps/beamline_driver/common/legacy_keys.py
aps/beamline_driver/common/utility.py
aps/beamline_driver/digital_twin/__init__.py
aps/beamline_driver/digital_twin/optimized_optics_manager.py
aps_beamline_driver-0.0.2.dist-info/licenses/LICENSE
aps_beamline_driver-0.0.2.dist-info/METADATA
aps_beamline_driver-0.0.2.dist-info/WHEEL
aps_beamline_driver-0.0.2.dist-info/top_level.txt
aps_beamline_driver-0.0.2.dist-info/RECORD
