Metadata-Version: 2.4
Name: aps-beamline-driver
Version: 0.0.2
Summary: APS Beamline Driver
Home-page: https://github.com/APS-XSD-OPT-Group/Beamline-Driver
Download-URL: https://github.com/APS-XSD-OPT-Group/Beamline-Driver
Author: Luca Rebuffi
Author-email: lrebuffi@anl.gov
Maintainer: XSD-OPT Group @ APS-ANL
Maintainer-email: lrebuffi@anl.gov
License: BSD-3
Keywords: dictionary,glossary,synchrotronsimulation
Classifier: Development Status :: 4 - Beta
Classifier: Environment :: X11 Applications :: Qt
Classifier: Environment :: Console
Classifier: Environment :: Plugins
Classifier: Programming Language :: Python
Classifier: Operating System :: POSIX
Classifier: Operating System :: Microsoft :: Windows
Classifier: Topic :: Scientific/Engineering :: Artificial Intelligence
Classifier: Topic :: Scientific/Engineering :: Visualization
Classifier: Topic :: Software Development :: Libraries :: Python Modules
Classifier: Intended Audience :: Education
Classifier: Intended Audience :: Science/Research
Classifier: Intended Audience :: Developers
License-File: LICENSE
Requires-Dist: aps-common-libraries>=1.0.17
Requires-Dist: cmasher
Dynamic: author
Dynamic: author-email
Dynamic: classifier
Dynamic: description
Dynamic: description-content-type
Dynamic: download-url
Dynamic: home-page
Dynamic: keywords
Dynamic: license
Dynamic: license-file
Dynamic: maintainer
Dynamic: maintainer-email
Dynamic: requires-dist
Dynamic: summary
